simyan/__init__.py
simyan/comicvine.py
simyan/exceptions.py
simyan/sqlite_cache.py
simyan/schemas/__init__.py
simyan/schemas/character.py
simyan/schemas/concept.py
simyan/schemas/creator.py
simyan/schemas/generic_entries.py
simyan/schemas/issue.py
simyan/schemas/item.py
simyan/schemas/location.py
simyan/schemas/origin.py
simyan/schemas/power.py
simyan/schemas/publisher.py
simyan/schemas/story_arc.py
simyan/schemas/team.py
simyan/schemas/volume.py
simyan-1.6.0.dist-info/METADATA
simyan-1.6.0.dist-info/WHEEL
simyan-1.6.0.dist-info/licenses/LICENSE
simyan-1.6.0.dist-info/RECORD
