Metadata-Version: 2.4
Name: Simyan
Version: 1.6.0
Summary: A Python wrapper for the Comicvine API.
Project-URL: Documentation, https://simyan.readthedocs.io/en/latest/
Project-URL: Homepage, https://pypi.org/project/Simyan
Project-URL: Issues, https://github.com/Metron-Project/Simyan/issues
Project-URL: Source, https://github.com/Metron-Project/Simyan
Author-email: BuriedInCode <BuriedInCode@tuta.io>
Maintainer-email: BuriedInCode <BuriedInCode@tuta.io>
License-Expression: GPL-3.0-or-later
License-File: LICENSE
Keywords: comic,comics,metadata
Classifier: Development Status :: 4 - Beta
Classifier: Environment :: Console
Classifier: Framework :: Pydantic :: 2
Classifier: Intended Audience :: Developers
Classifier: Natural Language :: English
Classifier: Operating System :: OS Independent
Classifier: Programming Language :: Python
Classifier: Programming Language :: Python :: 3.10
Classifier: Programming Language :: Python :: 3.11
Classifier: Programming Language :: Python :: 3.12
Classifier: Programming Language :: Python :: 3.13
Classifier: Programming Language :: Python :: 3.14
Classifier: Topic :: Internet
Classifier: Typing :: Typed
Requires-Python: >=3.10
Requires-Dist: pydantic>=2.12.0
Requires-Dist: pyrate-limiter>=3.9.0
Requires-Dist: requests>=2.32.0
